sherlock/__init__.py
sherlock/lock.py
sherlock-0.4.0.dist-info/LICENSE.rst
sherlock-0.4.0.dist-info/WHEEL
sherlock-0.4.0.dist-info/METADATA
sherlock-0.4.0.dist-info/RECORD
