Metadata-Version: 2.1
Name: sherlock
Version: 0.4.0
Summary: Distributed inter-process locks with a choice of backend
Home-page: https://github.com/py-sherlock/sherlock
License: MIT
Keywords: locking
Author: Vaidik Kapoor
Author-email: kapoor.vaidik@gmail.com
Maintainer: Vaidik Kapoor
Maintainer-email: kapoor.vaidik@gmail.com
Requires-Python: >=3.7,<4.0
Classifier: Development Status :: 2 - Pre-Alpha
Classifier: Intended Audience :: Developers
Classifier: License :: OSI Approved :: MIT License
Classifier: Operating System :: OS Independent
Classifier: Programming Language :: Python :: 3
Classifier: Programming Language :: Python :: 3.7
Classifier: Programming Language :: Python :: 3.8
Classifier: Programming Language :: Python :: 3.9
Classifier: Programming Language :: Python :: 3.10
Classifier: Programming Language :: Python :: 3.10
Classifier: Programming Language :: Python :: 3.7
Classifier: Programming Language :: Python :: 3.8
Classifier: Programming Language :: Python :: 3.9
Provides-Extra: all
Provides-Extra: etcd
Provides-Extra: filelock
Provides-Extra: kubernetes
Provides-Extra: memcached
Provides-Extra: redis
Requires-Dist: filelock (>=3.7.1,<4.0.0); extra == "all" or extra == "filelock"
Requires-Dist: kubernetes (>=24.2.0,<25.0.0); extra == "all" or extra == "kubernetes"
Requires-Dist: pylibmc (>=1.6.1,<2.0.0); extra == "all" or extra == "memcached"
Requires-Dist: python-etcd (>=0.4.5,<0.5.0); extra == "etcd"
Requires-Dist: redis (>=4.3.4,<5.0.0); extra == "all" or extra == "redis"
Project-URL: Repository, https://github.com/py-sherlock/sherlock
